{
	"ρ" : {
		"value" : 0.06,
		"description" : "Discount rate",
		"symbol" : "\\rho"
	},
  "σ" : {
		"value" : 2.0,
		"description" : "Intertemporal elasticity of substitution",
		"symbol" : "\\gamma"
	},
  "bmin" : {
		"value" : -2.0,
		"description" : "Lower bound on liquid asset",
		"symbol" : "\\bar{b}"
	},
  "bmax" : {
		"value" : 40.0,
		"description" : "Lower bound on liquid asset",
		"symbol" : "\\bar{b}"
	},
  "amax" : {
		"value" : 70.0,
		"description" : "Lower bound on liquid asset",
		"symbol" : "\\bar{b}"
	},
  "Δ" : {
		"value" : 100.0,
		"description" : "Time step",
		"symbol" : "\\Delta"
	},
  "χ0" : {
		"value" : 0.03,
		"description" : "Transaction cost, level",
		"symbol" : "\\Delta"
	},
  "χ1" : {
		"value" : 2.0,
		"description" : "Transaction cost, slope",
		"symbol" : "\\Delta"
	},
  "ξ" : {
		"value" : 0.1,
		"description" : "Fraction of income deposited in illiquid asset",
		"symbol" : "\\Delta"
	},
  "κ" : {
		"value" : 0.09,
		"description" : "Borrowing premium",
		"symbol" : "\\kappa"
	},
  "τ" : {
		"value" : 10.0,
		"description" : "Tax on illiquid return for large illiquid wealth",
		"symbol" : "\\tau"
	},
  "rb" : {
		"value" : 0.03,
		"description" : "Liquid return",
		"symbol" : "r\\_b"
	},
  "ra" : {
		"value" : 0.05,
		"description" : "Illiquid return ",
		"symbol" : "r\\_a"
	},
  "w" : {
		"value" : 4.0,
		"description" : "Wage rate",
		"symbol" : "w"
	},
  "nI" : {
		"value" : 80,
		"description" : "Grid size, liquid asset",
		"symbol" : "I"
	},
  "nJ" : {
		"value" : 50,
		"description" : "Grid size, illiquid asset",
		"symbol" : "I"
	},
  "nK" : {
		"value" : 4,
		"description" : "Grid size, productivity",
		"symbol" : "I"
	},
  "ρ_z" : {
		"value" : 0.7,
		"description" : "Persisence, AR1",
		"symbol" : "\\rho"
	},
  "σ2" : {
		"value" : 0.03,
		"description" : "Volatility, AR1",
		"symbol" : "\\sigma^2"
	},
  "ε" : {
		"value" : 1e-6,
		"description" : "Approximation error",
		"symbol" : "\\varepsilon"
	}
}
